{
  "project": "ohlcv-optimizer-v1",
  "version": 1,
  "saved_at": "20251215_141955",
  "meta": {
    "ranking_metric": "median_pnl_per_position_test",
    "candidate_pool": "pareto",
    "global_top_k": 50
  },
  "strategies_skipped": {
    "bollinger_breakout": "no_study",
    "range_breakout": "no_study",
    "stochastic": "no_study"
  },
  "champion_global": {
    "strategy": "rsi_reversion",
    "return_train_pct": 5.394403747224663,
    "dd_train_pct": 0.19832479605432587,
    "return_test_pct": 0.14164777193306222,
    "dd_test_pct": 3.537442624240905,
    "sharpe_train": 3.2324163708892124,
    "sharpe_test": 0.07149113291148967,
    "median_pnl_per_position_train": 50.473477335195795,
    "median_pnl_per_position_test": 40.90507964235443,
    "avg_pnl_per_position_train": 51.658105559609936,
    "avg_pnl_per_position_test": 9.065964113136529,
    "sharpe_pnl_per_position_train": 11.108577004136011,
    "sharpe_pnl_per_position_test": 0.3844879106069612,
    "median_pnl_per_position_train_pct": 0.504734773351958,
    "median_pnl_per_position_test_pct": 0.40905079642354436,
    "trades_train": 12,
    "trades_test": 12,
    "eligible": true,
    "trial": 447,
    "fast_period": NaN,
    "slow_period": NaN,
    "tp_mode": "rr",
    "tp_pct": NaN,
    "tp_mgmt": "full",
    "tp1_close_frac": NaN,
    "tp_trail_pct": NaN,
    "sl_type": "atr",
    "sl_trailing": false,
    "exit_on_flat": false,
    "sl_pct": NaN,
    "pm_mode": "grid",
    "tp_rr": 0.5019566305729979,
    "martingale_multiplier": NaN,
    "martingale_max_steps": NaN,
    "rsi_period": 35.0,
    "rsi_low_th": 21.76936946289403,
    "rsi_high_th": 84.39203712408185,
    "grid_max_adds": 3.0,
    "grid_spacing_pct": 0.47183977805878674,
    "grid_size_multiplier": 2.2131969678463204,
    "sl_atr_period": 23.0,
    "sl_atr_mult": 3.2160462393971967,
    "rank_pre_wf": 3,
    "rank_post_wf": 1,
    "rank_delta": -2
  },
  "champions_by_strategy": {
    "ma_cross": {
      "strategy": "ma_cross",
      "return_train_pct": -0.2793678787905818,
      "dd_train_pct": 2.8253231109164094,
      "return_test_pct": -1.353558615849726,
      "dd_test_pct": 3.529468109341617,
      "sharpe_train": -0.04873293388185697,
      "sharpe_test": -0.36987910635939647,
      "median_pnl_per_position_train": -2.7320993786985035,
      "median_pnl_per_position_test": -2.2619477172286926,
      "avg_pnl_per_position_train": 0.7822025913696643,
      "avg_pnl_per_position_test": 0.5761905899103716,
      "sharpe_pnl_per_position_train": 1.1340780749439598,
      "sharpe_pnl_per_position_test": 1.0500712041597393,
      "median_pnl_per_position_train_pct": -0.027320993786985038,
      "median_pnl_per_position_test_pct": -0.022619477172286927,
      "trades_train": 558,
      "trades_test": 559,
      "eligible": true,
      "trial": 357,
      "fast_period": 61.0,
      "slow_period": 233.0,
      "tp_mode": "pct",
      "tp_pct": 1.0037381001827224,
      "tp_mgmt": "partial_trailing",
      "tp1_close_frac": 0.35545091007233187,
      "tp_trail_pct": 4.752806736901484,
      "sl_type": "pct",
      "sl_trailing": false,
      "exit_on_flat": true,
      "sl_pct": 9.511010754681806,
      "pm_mode": "none",
      "tp_rr": NaN,
      "martingale_multiplier": NaN,
      "martingale_max_steps": NaN,
      "rsi_period": NaN,
      "rsi_low_th": NaN,
      "rsi_high_th": NaN,
      "grid_max_adds": NaN,
      "grid_spacing_pct": NaN,
      "grid_size_multiplier": NaN,
      "sl_atr_period": NaN,
      "sl_atr_mult": NaN,
      "rank_pre_wf": 12,
      "rank_post_wf": 10,
      "rank_delta": -2
    },
    "rsi_reversion": {
      "strategy": "rsi_reversion",
      "return_train_pct": 5.394403747224663,
      "dd_train_pct": 0.19832479605432587,
      "return_test_pct": 0.14164777193306222,
      "dd_test_pct": 3.537442624240905,
      "sharpe_train": 3.2324163708892124,
      "sharpe_test": 0.07149113291148967,
      "median_pnl_per_position_train": 50.473477335195795,
      "median_pnl_per_position_test": 40.90507964235443,
      "avg_pnl_per_position_train": 51.658105559609936,
      "avg_pnl_per_position_test": 9.065964113136529,
      "sharpe_pnl_per_position_train": 11.108577004136011,
      "sharpe_pnl_per_position_test": 0.3844879106069612,
      "median_pnl_per_position_train_pct": 0.504734773351958,
      "median_pnl_per_position_test_pct": 0.40905079642354436,
      "trades_train": 12,
      "trades_test": 12,
      "eligible": true,
      "trial": 447,
      "fast_period": NaN,
      "slow_period": NaN,
      "tp_mode": "rr",
      "tp_pct": NaN,
      "tp_mgmt": "full",
      "tp1_close_frac": NaN,
      "tp_trail_pct": NaN,
      "sl_type": "atr",
      "sl_trailing": false,
      "exit_on_flat": false,
      "sl_pct": NaN,
      "pm_mode": "grid",
      "tp_rr": 0.5019566305729979,
      "martingale_multiplier": NaN,
      "martingale_max_steps": NaN,
      "rsi_period": 35.0,
      "rsi_low_th": 21.76936946289403,
      "rsi_high_th": 84.39203712408185,
      "grid_max_adds": 3.0,
      "grid_spacing_pct": 0.47183977805878674,
      "grid_size_multiplier": 2.2131969678463204,
      "sl_atr_period": 23.0,
      "sl_atr_mult": 3.2160462393971967,
      "rank_pre_wf": 3,
      "rank_post_wf": 1,
      "rank_delta": -2
    }
  },
  "data": {
    "data_root": "C:\\Users\\Nahel\\Documents\\GitHub\\quantlab\\data\\market_data",
    "source": "binance_futures",
    "symbol": "BTC_USDC_USDC",
    "timeframe": "5m",
    "start_ms": 1704326400000,
    "end_ms": 1765756800000,
    "candles_total": 204495
  },
  "config": {
    "initial_equity": 10000.0,
    "fee_bps": 4.0,
    "slippage_bps": 0.5,
    "dd_threshold_pct": 40.0,
    "min_trades_train": 0,
    "min_trades_test": 0,
    "max_trials": 500,
    "time_budget_seconds": null,
    "timeframe": "5m",
    "pm_mode": "auto",
    "strategies": [
      "ma_cross",
      "rsi_reversion",
      "bollinger_breakout",
      "range_breakout",
      "stochastic"
    ],
    "pareto_candidates_max": 50,
    "candidate_pool": "pareto",
    "global_top_k": 50,
    "ranking_metric": "median_pnl_per_position_test",
    "train_frac": 0.5,
    "multiprocess": true,
    "workers": 8
  },
  "leaderboard": [
    {
      "strategy": "ma_cross",
      "return_train_pct": -0.2793678787905818,
      "dd_train_pct": 2.8253231109164094,
      "return_test_pct": -1.353558615849726,
      "dd_test_pct": 3.529468109341617,
      "sharpe_train": -0.04873293388185697,
      "sharpe_test": -0.36987910635939647,
      "median_pnl_per_position_train": -2.7320993786985035,
      "median_pnl_per_position_test": -2.2619477172286926,
      "avg_pnl_per_position_train": 0.7822025913696643,
      "avg_pnl_per_position_test": 0.5761905899103716,
      "sharpe_pnl_per_position_train": 1.1340780749439598,
      "sharpe_pnl_per_position_test": 1.0500712041597393,
      "median_pnl_per_position_train_pct": -0.027320993786985038,
      "median_pnl_per_position_test_pct": -0.022619477172286927,
      "trades_train": 558,
      "trades_test": 559,
      "eligible": true,
      "trial": 357,
      "fast_period": 61.0,
      "slow_period": 233.0,
      "tp_mode": "pct",
      "tp_pct": 1.0037381001827224,
      "tp_mgmt": "partial_trailing",
      "tp1_close_frac": 0.35545091007233187,
      "tp_trail_pct": 4.752806736901484,
      "sl_type": "pct",
      "sl_trailing": false,
      "exit_on_flat": true,
      "sl_pct": 9.511010754681806,
      "pm_mode": "none",
      "tp_rr": NaN,
      "martingale_multiplier": NaN,
      "martingale_max_steps": NaN,
      "rsi_period": NaN,
      "rsi_low_th": NaN,
      "rsi_high_th": NaN,
      "grid_max_adds": NaN,
      "grid_spacing_pct": NaN,
      "grid_size_multiplier": NaN,
      "sl_atr_period": NaN,
      "sl_atr_mult": NaN,
      "rank_pre_wf": 12,
      "rank_post_wf": 10,
      "rank_delta": -2
    },
    {
      "strategy": "rsi_reversion",
      "return_train_pct": 5.394403747224663,
      "dd_train_pct": 0.19832479605432587,
      "return_test_pct": 0.14164777193306222,
      "dd_test_pct": 3.537442624240905,
      "sharpe_train": 3.2324163708892124,
      "sharpe_test": 0.07149113291148967,
      "median_pnl_per_position_train": 50.473477335195795,
      "median_pnl_per_position_test": 40.90507964235443,
      "avg_pnl_per_position_train": 51.658105559609936,
      "avg_pnl_per_position_test": 9.065964113136529,
      "sharpe_pnl_per_position_train": 11.108577004136011,
      "sharpe_pnl_per_position_test": 0.3844879106069612,
      "median_pnl_per_position_train_pct": 0.504734773351958,
      "median_pnl_per_position_test_pct": 0.40905079642354436,
      "trades_train": 12,
      "trades_test": 12,
      "eligible": true,
      "trial": 447,
      "fast_period": NaN,
      "slow_period": NaN,
      "tp_mode": "rr",
      "tp_pct": NaN,
      "tp_mgmt": "full",
      "tp1_close_frac": NaN,
      "tp_trail_pct": NaN,
      "sl_type": "atr",
      "sl_trailing": false,
      "exit_on_flat": false,
      "sl_pct": NaN,
      "pm_mode": "grid",
      "tp_rr": 0.5019566305729979,
      "martingale_multiplier": NaN,
      "martingale_max_steps": NaN,
      "rsi_period": 35.0,
      "rsi_low_th": 21.76936946289403,
      "rsi_high_th": 84.39203712408185,
      "grid_max_adds": 3.0,
      "grid_spacing_pct": 0.47183977805878674,
      "grid_size_multiplier": 2.2131969678463204,
      "sl_atr_period": 23.0,
      "sl_atr_mult": 3.2160462393971967,
      "rank_pre_wf": 3,
      "rank_post_wf": 1,
      "rank_delta": -2
    }
  ],
  "global_leaderboard": [
    {
      "strategy": "rsi_reversion",
      "return_train_pct": 5.394403747224663,
      "dd_train_pct": 0.19832479605432587,
      "return_test_pct": 0.14164777193306222,
      "dd_test_pct": 3.537442624240905,
      "sharpe_train": 3.2324163708892124,
      "sharpe_test": 0.07149113291148967,
      "median_pnl_per_position_train": 50.473477335195795,
      "median_pnl_per_position_test": 40.90507964235443,
      "avg_pnl_per_position_train": 51.658105559609936,
      "avg_pnl_per_position_test": 9.065964113136529,
      "sharpe_pnl_per_position_train": 11.108577004136011,
      "sharpe_pnl_per_position_test": 0.3844879106069612,
      "median_pnl_per_position_train_pct": 0.504734773351958,
      "median_pnl_per_position_test_pct": 0.40905079642354436,
      "trades_train": 12,
      "trades_test": 12,
      "eligible": true,
      "trial": 447,
      "fast_period": NaN,
      "slow_period": NaN,
      "tp_mode": "rr",
      "tp_pct": NaN,
      "tp_mgmt": "full",
      "tp1_close_frac": NaN,
      "tp_trail_pct": NaN,
      "sl_type": "atr",
      "sl_trailing": false,
      "exit_on_flat": false,
      "sl_pct": NaN,
      "pm_mode": "grid",
      "tp_rr": 0.5019566305729979,
      "martingale_multiplier": NaN,
      "martingale_max_steps": NaN,
      "rsi_period": 35.0,
      "rsi_low_th": 21.76936946289403,
      "rsi_high_th": 84.39203712408185,
      "grid_max_adds": 3.0,
      "grid_spacing_pct": 0.47183977805878674,
      "grid_size_multiplier": 2.2131969678463204,
      "sl_atr_period": 23.0,
      "sl_atr_mult": 3.2160462393971967,
      "rank_pre_wf": 3,
      "rank_post_wf": 1,
      "rank_delta": -2
    },
    {
      "strategy": "rsi_reversion",
      "return_train_pct": 1.7443756549314626,
      "dd_train_pct": 0.0,
      "return_test_pct": -1.840656323306844,
      "dd_test_pct": 2.3801387600231214,
      "sharpe_train": 3.00012599278936,
      "sharpe_test": -1.354850741496529,
      "median_pnl_per_position_train": 27.427052425536004,
      "median_pnl_per_position_test": 26.629343693485062,
      "avg_pnl_per_position_train": 27.45896851859611,
      "avg_pnl_per_position_test": -8.801700166000021,
      "sharpe_pnl_per_position_train": 477.7404804054107,
      "sharpe_pnl_per_position_test": -0.5854292297664013,
      "median_pnl_per_position_train_pct": 0.27427052425536,
      "median_pnl_per_position_test_pct": 0.26629343693485064,
      "trades_train": 9,
      "trades_test": 11,
      "eligible": true,
      "trial": 351,
      "fast_period": NaN,
      "slow_period": NaN,
      "tp_mode": "pct",
      "tp_pct": 0.27718603640329753,
      "tp_mgmt": "full",
      "tp1_close_frac": NaN,
      "tp_trail_pct": NaN,
      "sl_type": "pct",
      "sl_trailing": false,
      "exit_on_flat": true,
      "sl_pct": 0.8871505665169417,
      "pm_mode": "grid",
      "tp_rr": NaN,
      "martingale_multiplier": NaN,
      "martingale_max_steps": NaN,
      "rsi_period": 39.0,
      "rsi_low_th": 22.1346051164859,
      "rsi_high_th": 84.92633605937283,
      "grid_max_adds": 1.0,
      "grid_spacing_pct": 0.5494617764730851,
      "grid_size_multiplier": 1.3477002004001313,
      "sl_atr_period": NaN,
      "sl_atr_mult": NaN,
      "rank_pre_wf": 8,
      "rank_post_wf": 2,
      "rank_delta": -6
    },
    {
      "strategy": "rsi_reversion",
      "return_train_pct": 4.107154523852707,
      "dd_train_pct": 0.12567295711652077,
      "return_test_pct": 3.8947757016039475,
      "dd_test_pct": 2.0254771718723865,
      "sharpe_train": 1.95407034796315,
      "sharpe_test": 0.7921741113442001,
      "median_pnl_per_position_train": 34.936350217531725,
      "median_pnl_per_position_test": 12.122548734905301,
      "avg_pnl_per_position_train": 65.31326990720245,
      "avg_pnl_per_position_test": 61.43535010671952,
      "sharpe_pnl_per_position_train": 3.634672670318763,
      "sharpe_pnl_per_position_test": 0.8784871372533586,
      "median_pnl_per_position_train_pct": 0.34936350217531725,
      "median_pnl_per_position_test_pct": 0.12122548734905302,
      "trades_train": 7,
      "trades_test": 7,
      "eligible": true,
      "trial": 295,
      "fast_period": NaN,
      "slow_period": NaN,
      "tp_mode": "pct",
      "tp_pct": 8.841607960886753,
      "tp_mgmt": "full",
      "tp1_close_frac": NaN,
      "tp_trail_pct": NaN,
      "sl_type": "pct",
      "sl_trailing": false,
      "exit_on_flat": true,
      "sl_pct": 2.4247300906303164,
      "pm_mode": "grid",
      "tp_rr": NaN,
      "martingale_multiplier": NaN,
      "martingale_max_steps": NaN,
      "rsi_period": 39.0,
      "rsi_low_th": 22.1346051164859,
      "rsi_high_th": 84.92633605937283,
      "grid_max_adds": 8.0,
      "grid_spacing_pct": 0.2979100139044504,
      "grid_size_multiplier": 1.3147961401758106,
      "sl_atr_period": NaN,
      "sl_atr_mult": NaN,
      "rank_pre_wf": 6,
      "rank_post_wf": 3,
      "rank_delta": -3
    },
    {
      "strategy": "rsi_reversion",
      "return_train_pct": 4.4112122540997944,
      "dd_train_pct": 0.16753539699671563,
      "return_test_pct": 5.023845651273451,
      "dd_test_pct": 2.32065286352767,
      "sharpe_train": 2.7666977017257235,
      "sharpe_test": 0.8817779328763898,
      "median_pnl_per_position_train": 29.885607804268957,
      "median_pnl_per_position_test": 11.055851484394378,
      "avg_pnl_per_position_train": 32.921468875217386,
      "avg_pnl_per_position_test": 38.92348965008183,
      "sharpe_pnl_per_position_train": 5.61197455698795,
      "sharpe_pnl_per_position_test": 1.0971319689345558,
      "median_pnl_per_position_train_pct": 0.2988560780426896,
      "median_pnl_per_position_test_pct": 0.11055851484394377,
      "trades_train": 16,
      "trades_test": 16,
      "eligible": true,
      "trial": 457,
      "fast_period": NaN,
      "slow_period": NaN,
      "tp_mode": "pct",
      "tp_pct": 8.971486228613307,
      "tp_mgmt": "full",
      "tp1_close_frac": NaN,
      "tp_trail_pct": NaN,
      "sl_type": "atr",
      "sl_trailing": false,
      "exit_on_flat": true,
      "sl_pct": NaN,
      "pm_mode": "grid",
      "tp_rr": NaN,
      "martingale_multiplier": NaN,
      "martingale_max_steps": NaN,
      "rsi_period": 33.0,
      "rsi_low_th": 21.76936946289403,
      "rsi_high_th": 84.39203712408185,
      "grid_max_adds": 7.0,
      "grid_spacing_pct": 0.5927429543084243,
      "grid_size_multiplier": 1.99827167948165,
      "sl_atr_period": 34.0,
      "sl_atr_mult": 5.798232052198718,
      "rank_pre_wf": 7,
      "rank_post_wf": 4,
      "rank_delta": -3
    },
    {
      "strategy": "rsi_reversion",
      "return_train_pct": 7.6022401920968985,
      "dd_train_pct": 1.2945792347880616,
      "return_test_pct": -1.9223890012866618,
      "dd_test_pct": 3.8262605315003007,
      "sharpe_train": 2.5076232901897897,
      "sharpe_test": -1.0130560462441465,
      "median_pnl_per_position_train": 44.802446081197544,
      "median_pnl_per_position_test": 9.380132321507856,
      "avg_pnl_per_position_train": 47.120327691219074,
      "avg_pnl_per_position_test": -3.616940054216144,
      "sharpe_pnl_per_position_train": 3.64561457553551,
      "sharpe_pnl_per_position_test": -0.3451615210889119,
      "median_pnl_per_position_train_pct": 0.44802446081197544,
      "median_pnl_per_position_test_pct": 0.09380132321507856,
      "trades_train": 19,
      "trades_test": 18,
      "eligible": true,
      "trial": 335,
      "fast_period": NaN,
      "slow_period": NaN,
      "tp_mode": "rr",
      "tp_pct": NaN,
      "tp_mgmt": "full",
      "tp1_close_frac": NaN,
      "tp_trail_pct": NaN,
      "sl_type": "pct",
      "sl_trailing": false,
      "exit_on_flat": true,
      "sl_pct": 1.1680340385076784,
      "pm_mode": "grid",
      "tp_rr": 8.325560679027674,
      "martingale_multiplier": NaN,
      "martingale_max_steps": NaN,
      "rsi_period": 33.0,
      "rsi_low_th": 22.1346051164859,
      "rsi_high_th": 84.92633605937283,
      "grid_max_adds": 7.0,
      "grid_spacing_pct": 0.7304850162650767,
      "grid_size_multiplier": 2.224481582270542,
      "sl_atr_period": NaN,
      "sl_atr_mult": NaN,
      "rank_pre_wf": 4,
      "rank_post_wf": 5,
      "rank_delta": 1
    },
    {
      "strategy": "rsi_reversion",
      "return_train_pct": 45.04338215643588,
      "dd_train_pct": 10.556212289333153,
      "return_test_pct": 11.953604994222488,
      "dd_test_pct": 14.133269080592653,
      "sharpe_train": 1.9464856828528256,
      "sharpe_test": 0.7252782879716557,
      "median_pnl_per_position_train": 11.770846112717255,
      "median_pnl_per_position_test": 8.93362338126239,
      "avg_pnl_per_position_train": 21.22602018747915,
      "avg_pnl_per_position_test": 8.143233802548359,
      "sharpe_pnl_per_position_train": 2.2951455933342553,
      "sharpe_pnl_per_position_test": 1.1470308644655487,
      "median_pnl_per_position_train_pct": 0.11770846112717254,
      "median_pnl_per_position_test_pct": 0.0893362338126239,
      "trades_train": 238,
      "trades_test": 201,
      "eligible": true,
      "trial": 214,
      "fast_period": NaN,
      "slow_period": NaN,
      "tp_mode": "rr",
      "tp_pct": NaN,
      "tp_mgmt": "full",
      "tp1_close_frac": NaN,
      "tp_trail_pct": NaN,
      "sl_type": "pct",
      "sl_trailing": false,
      "exit_on_flat": false,
      "sl_pct": 9.91979250163157,
      "pm_mode": "martingale",
      "tp_rr": 7.936687497545588,
      "martingale_multiplier": 3.274373827035542,
      "martingale_max_steps": 5.0,
      "rsi_period": 12.0,
      "rsi_low_th": 23.32484642715096,
      "rsi_high_th": 80.81420691980657,
      "grid_max_adds": NaN,
      "grid_spacing_pct": NaN,
      "grid_size_multiplier": NaN,
      "sl_atr_period": NaN,
      "sl_atr_mult": NaN,
      "rank_pre_wf": 11,
      "rank_post_wf": 6,
      "rank_delta": -5
    },
    {
      "strategy": "rsi_reversion",
      "return_train_pct": 1.8257357561089815,
      "dd_train_pct": 0.09247549721998827,
      "return_test_pct": -0.3627753669226186,
      "dd_test_pct": 1.1509090902175558,
      "sharpe_train": 2.7523838592590124,
      "sharpe_test": -0.5041081975153481,
      "median_pnl_per_position_train": 13.306377284222943,
      "median_pnl_per_position_test": 6.885509730136404,
      "avg_pnl_per_position_train": 14.107228233638178,
      "avg_pnl_per_position_test": 1.5024616628085035,
      "sharpe_pnl_per_position_train": 7.448357286593122,
      "sharpe_pnl_per_position_test": 0.21674717322685105,
      "median_pnl_per_position_train_pct": 0.13306377284222942,
      "median_pnl_per_position_test_pct": 0.06885509730136403,
      "trades_train": 16,
      "trades_test": 16,
      "eligible": true,
      "trial": 287,
      "fast_period": NaN,
      "slow_period": NaN,
      "tp_mode": "pct",
      "tp_pct": 2.3693395275442612,
      "tp_mgmt": "full",
      "tp1_close_frac": NaN,
      "tp_trail_pct": NaN,
      "sl_type": "atr",
      "sl_trailing": false,
      "exit_on_flat": true,
      "sl_pct": NaN,
      "pm_mode": "grid",
      "tp_rr": NaN,
      "martingale_multiplier": NaN,
      "martingale_max_steps": NaN,
      "rsi_period": 33.0,
      "rsi_low_th": 21.76936946289403,
      "rsi_high_th": 84.39203712408185,
      "grid_max_adds": 1.0,
      "grid_spacing_pct": 2.5940967032002287,
      "grid_size_multiplier": 1.272139610333226,
      "sl_atr_period": 8.0,
      "sl_atr_mult": 5.749914071211865,
      "rank_pre_wf": 10,
      "rank_post_wf": 7,
      "rank_delta": -3
    },
    {
      "strategy": "rsi_reversion",
      "return_train_pct": 6.875184555534153,
      "dd_train_pct": 0.21051871725322,
      "return_test_pct": -1.9969138450876,
      "dd_test_pct": 3.2927902556712665,
      "sharpe_train": 2.722866362654811,
      "sharpe_test": -1.2059137733615,
      "median_pnl_per_position_train": 37.13349779635951,
      "median_pnl_per_position_test": 6.319849219546902,
      "avg_pnl_per_position_train": 49.32444442766153,
      "avg_pnl_per_position_test": -6.528157153118264,
      "sharpe_pnl_per_position_train": 4.728043471077624,
      "sharpe_pnl_per_position_test": -0.503605886436222,
      "median_pnl_per_position_train_pct": 0.37133497796359505,
      "median_pnl_per_position_test_pct": 0.06319849219546902,
      "trades_train": 16,
      "trades_test": 16,
      "eligible": true,
      "trial": 412,
      "fast_period": NaN,
      "slow_period": NaN,
      "tp_mode": "pct",
      "tp_pct": 9.776612124162286,
      "tp_mgmt": "full",
      "tp1_close_frac": NaN,
      "tp_trail_pct": NaN,
      "sl_type": "pct",
      "sl_trailing": false,
      "exit_on_flat": true,
      "sl_pct": 1.6957643142047478,
      "pm_mode": "grid",
      "tp_rr": NaN,
      "martingale_multiplier": NaN,
      "martingale_max_steps": NaN,
      "rsi_period": 33.0,
      "rsi_low_th": 21.76936946289403,
      "rsi_high_th": 84.92633605937283,
      "grid_max_adds": 7.0,
      "grid_spacing_pct": 0.29283882846536496,
      "grid_size_multiplier": 2.2095969504119815,
      "sl_atr_period": NaN,
      "sl_atr_mult": NaN,
      "rank_pre_wf": 5,
      "rank_post_wf": 8,
      "rank_delta": 3
    },
    {
      "strategy": "rsi_reversion",
      "return_train_pct": 2.137250923867051,
      "dd_train_pct": 0.09690947255616146,
      "return_test_pct": 0.643061809863954,
      "dd_test_pct": 0.977649722894227,
      "sharpe_train": 2.8168746608374393,
      "sharpe_test": 0.48019805244626784,
      "median_pnl_per_position_train": 14.134297157824959,
      "median_pnl_per_position_test": 3.7956133103986653,
      "avg_pnl_per_position_train": 16.5142989439952,
      "avg_pnl_per_position_test": 6.757801978934782,
      "sharpe_pnl_per_position_train": 5.855699433202037,
      "sharpe_pnl_per_position_test": 0.7057027295416126,
      "median_pnl_per_position_train_pct": 0.1413429715782496,
      "median_pnl_per_position_test_pct": 0.03795613310398665,
      "trades_train": 15,
      "trades_test": 15,
      "eligible": true,
      "trial": 399,
      "fast_period": NaN,
      "slow_period": NaN,
      "tp_mode": "pct",
      "tp_pct": 5.540335935004982,
      "tp_mgmt": "partial_trailing",
      "tp1_close_frac": 0.45322440109870166,
      "tp_trail_pct": 4.444135704653584,
      "sl_type": "pct",
      "sl_trailing": true,
      "exit_on_flat": true,
      "sl_pct": 3.574058624265579,
      "pm_mode": "martingale",
      "tp_rr": NaN,
      "martingale_multiplier": 1.3368141902476345,
      "martingale_max_steps": 2.0,
      "rsi_period": 33.0,
      "rsi_low_th": 21.76936946289403,
      "rsi_high_th": 87.44816828888347,
      "grid_max_adds": NaN,
      "grid_spacing_pct": NaN,
      "grid_size_multiplier": NaN,
      "sl_atr_period": NaN,
      "sl_atr_mult": NaN,
      "rank_pre_wf": 9,
      "rank_post_wf": 9,
      "rank_delta": 0
    },
    {
      "strategy": "ma_cross",
      "return_train_pct": -0.2793678787905818,
      "dd_train_pct": 2.8253231109164094,
      "return_test_pct": -1.353558615849726,
      "dd_test_pct": 3.529468109341617,
      "sharpe_train": -0.04873293388185697,
      "sharpe_test": -0.36987910635939647,
      "median_pnl_per_position_train": -2.7320993786985035,
      "median_pnl_per_position_test": -2.2619477172286926,
      "avg_pnl_per_position_train": 0.7822025913696643,
      "avg_pnl_per_position_test": 0.5761905899103716,
      "sharpe_pnl_per_position_train": 1.1340780749439598,
      "sharpe_pnl_per_position_test": 1.0500712041597393,
      "median_pnl_per_position_train_pct": -0.027320993786985038,
      "median_pnl_per_position_test_pct": -0.022619477172286927,
      "trades_train": 558,
      "trades_test": 559,
      "eligible": true,
      "trial": 357,
      "fast_period": 61.0,
      "slow_period": 233.0,
      "tp_mode": "pct",
      "tp_pct": 1.0037381001827224,
      "tp_mgmt": "partial_trailing",
      "tp1_close_frac": 0.35545091007233187,
      "tp_trail_pct": 4.752806736901484,
      "sl_type": "pct",
      "sl_trailing": false,
      "exit_on_flat": true,
      "sl_pct": 9.511010754681806,
      "pm_mode": "none",
      "tp_rr": NaN,
      "martingale_multiplier": NaN,
      "martingale_max_steps": NaN,
      "rsi_period": NaN,
      "rsi_low_th": NaN,
      "rsi_high_th": NaN,
      "grid_max_adds": NaN,
      "grid_spacing_pct": NaN,
      "grid_size_multiplier": NaN,
      "sl_atr_period": NaN,
      "sl_atr_mult": NaN,
      "rank_pre_wf": 12,
      "rank_post_wf": 10,
      "rank_delta": -2
    },
    {
      "strategy": "ma_cross",
      "return_train_pct": 1.4302608903856484,
      "dd_train_pct": 3.5490158629147763,
      "return_test_pct": -0.4892170873518453,
      "dd_test_pct": 4.632184836414822,
      "sharpe_train": 0.2887519477093766,
      "sharpe_test": -0.08294677719877921,
      "median_pnl_per_position_train": -4.631671334389963,
      "median_pnl_per_position_test": -3.4640820931894765,
      "avg_pnl_per_position_train": 1.1363952850461743,
      "avg_pnl_per_position_test": 0.7061897019446246,
      "sharpe_pnl_per_position_train": 1.0499799117356168,
      "sharpe_pnl_per_position_test": 0.8787688011859844,
      "median_pnl_per_position_train_pct": -0.046316713343899626,
      "median_pnl_per_position_test_pct": -0.034640820931894765,
      "trades_train": 479,
      "trades_test": 485,
      "eligible": true,
      "trial": 114,
      "fast_period": 77.0,
      "slow_period": 221.0,
      "tp_mode": "rr",
      "tp_pct": NaN,
      "tp_mgmt": "partial_trailing",
      "tp1_close_frac": 0.3620279821590059,
      "tp_trail_pct": 0.48745040707794407,
      "sl_type": "pct",
      "sl_trailing": true,
      "exit_on_flat": false,
      "sl_pct": 9.638542325417848,
      "pm_mode": "none",
      "tp_rr": 9.696857208969782,
      "martingale_multiplier": NaN,
      "martingale_max_steps": NaN,
      "rsi_period": NaN,
      "rsi_low_th": NaN,
      "rsi_high_th": NaN,
      "grid_max_adds": NaN,
      "grid_spacing_pct": NaN,
      "grid_size_multiplier": NaN,
      "sl_atr_period": NaN,
      "sl_atr_mult": NaN,
      "rank_pre_wf": 13,
      "rank_post_wf": 11,
      "rank_delta": -2
    },
    {
      "strategy": "ma_cross",
      "return_train_pct": 3.4786671951661408,
      "dd_train_pct": 3.8590242755506954,
      "return_test_pct": 0.002079323136672251,
      "dd_test_pct": 4.784487280334547,
      "sharpe_train": 0.6105711181107416,
      "sharpe_test": 0.02534199015710188,
      "median_pnl_per_position_train": -5.290581361090543,
      "median_pnl_per_position_test": -4.341361976857023,
      "avg_pnl_per_position_train": 1.6466498130377825,
      "avg_pnl_per_position_test": 0.8595506357927247,
      "sharpe_pnl_per_position_train": 1.2447589673891508,
      "sharpe_pnl_per_position_test": 0.7911688659202996,
      "median_pnl_per_position_train_pct": -0.052905813610905426,
      "median_pnl_per_position_test_pct": -0.04341361976857023,
      "trades_train": 463,
      "trades_test": 458,
      "eligible": true,
      "trial": 123,
      "fast_period": 80.0,
      "slow_period": 237.0,
      "tp_mode": "pct",
      "tp_pct": 8.519808331527988,
      "tp_mgmt": "full",
      "tp1_close_frac": NaN,
      "tp_trail_pct": NaN,
      "sl_type": "pct",
      "sl_trailing": false,
      "exit_on_flat": false,
      "sl_pct": 8.997497204480387,
      "pm_mode": "none",
      "tp_rr": NaN,
      "martingale_multiplier": NaN,
      "martingale_max_steps": NaN,
      "rsi_period": NaN,
      "rsi_low_th": NaN,
      "rsi_high_th": NaN,
      "grid_max_adds": NaN,
      "grid_spacing_pct": NaN,
      "grid_size_multiplier": NaN,
      "sl_atr_period": NaN,
      "sl_atr_mult": NaN,
      "rank_pre_wf": 14,
      "rank_post_wf": 12,
      "rank_delta": -2
    },
    {
      "strategy": "ma_cross",
      "return_train_pct": 4.1262105706299845,
      "dd_train_pct": 5.645006812587834,
      "return_test_pct": -1.9526843851176423,
      "dd_test_pct": 7.195744858099759,
      "sharpe_train": 0.5059386322189146,
      "sharpe_test": -0.22866913909648254,
      "median_pnl_per_position_train": -6.908176377356696,
      "median_pnl_per_position_test": -6.079383204661566,
      "avg_pnl_per_position_train": 2.2337335031485366,
      "avg_pnl_per_position_test": 0.8431518051066299,
      "sharpe_pnl_per_position_train": 1.2279903471851745,
      "sharpe_pnl_per_position_test": 0.6127285718914047,
      "median_pnl_per_position_train_pct": -0.06908176377356696,
      "median_pnl_per_position_test_pct": -0.060793832046615655,
      "trades_train": 454,
      "trades_test": 458,
      "eligible": true,
      "trial": 391,
      "fast_period": 77.0,
      "slow_period": 246.0,
      "tp_mode": "rr",
      "tp_pct": NaN,
      "tp_mgmt": "partial_trailing",
      "tp1_close_frac": 0.8271175302890283,
      "tp_trail_pct": 1.6735210475113522,
      "sl_type": "pct",
      "sl_trailing": true,
      "exit_on_flat": false,
      "sl_pct": 6.006872529289809,
      "pm_mode": "none",
      "tp_rr": 6.056171015030701,
      "martingale_multiplier": NaN,
      "martingale_max_steps": NaN,
      "rsi_period": NaN,
      "rsi_low_th": NaN,
      "rsi_high_th": NaN,
      "grid_max_adds": NaN,
      "grid_spacing_pct": NaN,
      "grid_size_multiplier": NaN,
      "sl_atr_period": NaN,
      "sl_atr_mult": NaN,
      "rank_pre_wf": 15,
      "rank_post_wf": 13,
      "rank_delta": -2
    },
    {
      "strategy": "ma_cross",
      "return_train_pct": 10.621979440423557,
      "dd_train_pct": 7.568965503791947,
      "return_test_pct": -1.429058298503938,
      "dd_test_pct": 10.829763341111482,
      "sharpe_train": 0.833621571629342,
      "sharpe_test": -0.07742740617907748,
      "median_pnl_per_position_train": -9.49154766120596,
      "median_pnl_per_position_test": -6.200874732207479,
      "avg_pnl_per_position_train": 4.141301023999896,
      "avg_pnl_per_position_test": 1.4708603658358474,
      "sharpe_pnl_per_position_train": 1.5590002800733112,
      "sharpe_pnl_per_position_test": 0.8381284608409911,
      "median_pnl_per_position_train_pct": -0.0949154766120596,
      "median_pnl_per_position_test_pct": -0.06200874732207479,
      "trades_train": 493,
      "trades_test": 513,
      "eligible": true,
      "trial": 491,
      "fast_period": 77.0,
      "slow_period": 205.0,
      "tp_mode": "rr",
      "tp_pct": NaN,
      "tp_mgmt": "full",
      "tp1_close_frac": NaN,
      "tp_trail_pct": NaN,
      "sl_type": "pct",
      "sl_trailing": false,
      "exit_on_flat": false,
      "sl_pct": 7.589035468740991,
      "pm_mode": "martingale",
      "tp_rr": 9.14984211071049,
      "martingale_multiplier": 2.1176869269504532,
      "martingale_max_steps": 1.0,
      "rsi_period": NaN,
      "rsi_low_th": NaN,
      "rsi_high_th": NaN,
      "grid_max_adds": NaN,
      "grid_spacing_pct": NaN,
      "grid_size_multiplier": NaN,
      "sl_atr_period": NaN,
      "sl_atr_mult": NaN,
      "rank_pre_wf": 18,
      "rank_post_wf": 14,
      "rank_delta": -4
    },
    {
      "strategy": "ma_cross",
      "return_train_pct": 8.995618565791341,
      "dd_train_pct": 6.774283474551231,
      "return_test_pct": -0.9474188606042988,
      "dd_test_pct": 8.531247025533839,
      "sharpe_train": 0.8731036397010942,
      "sharpe_test": -0.0653580440229923,
      "median_pnl_per_position_train": -7.8667503663677945,
      "median_pnl_per_position_test": -6.6349208561066195,
      "avg_pnl_per_position_train": 3.544213741600866,
      "avg_pnl_per_position_test": 1.2391621966234116,
      "sharpe_pnl_per_position_train": 1.5623191786163664,
      "sharpe_pnl_per_position_test": 0.7698144906437789,
      "median_pnl_per_position_train_pct": -0.07866750366367795,
      "median_pnl_per_position_test_pct": -0.06634920856106619,
      "trades_train": 460,
      "trades_test": 456,
      "eligible": true,
      "trial": 352,
      "fast_period": 77.0,
      "slow_period": 234.0,
      "tp_mode": "rr",
      "tp_pct": NaN,
      "tp_mgmt": "partial_trailing",
      "tp1_close_frac": 0.7611659728861934,
      "tp_trail_pct": 1.6342455251015282,
      "sl_type": "pct",
      "sl_trailing": false,
      "exit_on_flat": true,
      "sl_pct": 8.965679962112384,
      "pm_mode": "martingale",
      "tp_rr": 5.151473249989,
      "martingale_multiplier": 2.0035441128987,
      "martingale_max_steps": 1.0,
      "rsi_period": NaN,
      "rsi_low_th": NaN,
      "rsi_high_th": NaN,
      "grid_max_adds": NaN,
      "grid_spacing_pct": NaN,
      "grid_size_multiplier": NaN,
      "sl_atr_period": NaN,
      "sl_atr_mult": NaN,
      "rank_pre_wf": 16,
      "rank_post_wf": 15,
      "rank_delta": -1
    },
    {
      "strategy": "ma_cross",
      "return_train_pct": 21.481393288957996,
      "dd_train_pct": 8.507971239405125,
      "return_test_pct": 4.127582947949127,
      "dd_test_pct": 11.645790955717846,
      "sharpe_train": 1.2861757049421472,
      "sharpe_test": 0.358540726838893,
      "median_pnl_per_position_train": -8.905434384327148,
      "median_pnl_per_position_test": -6.761070741837362,
      "avg_pnl_per_position_train": 6.9580232392570185,
      "avg_pnl_per_position_test": 3.2569701204169608,
      "sharpe_pnl_per_position_train": 1.9614787825786375,
      "sharpe_pnl_per_position_test": 1.1108186411770025,
      "median_pnl_per_position_train_pct": -0.08905434384327147,
      "median_pnl_per_position_test_pct": -0.06761070741837362,
      "trades_train": 502,
      "trades_test": 487,
      "eligible": true,
      "trial": 250,
      "fast_period": 77.0,
      "slow_period": 227.0,
      "tp_mode": "pct",
      "tp_pct": 3.6401063391154644,
      "tp_mgmt": "partial_trailing",
      "tp1_close_frac": 0.6114594067607179,
      "tp_trail_pct": 3.968704253518172,
      "sl_type": "pct",
      "sl_trailing": false,
      "exit_on_flat": false,
      "sl_pct": 8.10576938549548,
      "pm_mode": "martingale",
      "tp_rr": NaN,
      "martingale_multiplier": 1.413287149021479,
      "martingale_max_steps": 7.0,
      "rsi_period": NaN,
      "rsi_low_th": NaN,
      "rsi_high_th": NaN,
      "grid_max_adds": NaN,
      "grid_spacing_pct": NaN,
      "grid_size_multiplier": NaN,
      "sl_atr_period": NaN,
      "sl_atr_mult": NaN,
      "rank_pre_wf": 17,
      "rank_post_wf": 16,
      "rank_delta": -1
    },
    {
      "strategy": "ma_cross",
      "return_train_pct": 64.90659026619731,
      "dd_train_pct": 14.245870539899702,
      "return_test_pct": 2.6799477344289,
      "dd_test_pct": 21.86272811672797,
      "sharpe_train": 1.8946705672863506,
      "sharpe_test": 0.22996718602163613,
      "median_pnl_per_position_train": -12.855576311304466,
      "median_pnl_per_position_test": -6.952978516871251,
      "avg_pnl_per_position_train": 17.322178147560365,
      "avg_pnl_per_position_test": 3.7836044980792742,
      "sharpe_pnl_per_position_train": 2.397573208788453,
      "sharpe_pnl_per_position_test": 0.9612582726764105,
      "median_pnl_per_position_train_pct": -0.12855576311304467,
      "median_pnl_per_position_test_pct": -0.0695297851687125,
      "trades_train": 518,
      "trades_test": 527,
      "eligible": true,
      "trial": 244,
      "fast_period": 77.0,
      "slow_period": 205.0,
      "tp_mode": "pct",
      "tp_pct": 7.557477723750414,
      "tp_mgmt": "partial_trailing",
      "tp1_close_frac": 0.631134681197562,
      "tp_trail_pct": 2.577462348978059,
      "sl_type": "pct",
      "sl_trailing": false,
      "exit_on_flat": true,
      "sl_pct": 9.728169021691793,
      "pm_mode": "martingale",
      "tp_rr": NaN,
      "martingale_multiplier": 1.9503547585390013,
      "martingale_max_steps": 7.0,
      "rsi_period": NaN,
      "rsi_low_th": NaN,
      "rsi_high_th": NaN,
      "grid_max_adds": NaN,
      "grid_spacing_pct": NaN,
      "grid_size_multiplier": NaN,
      "sl_atr_period": NaN,
      "sl_atr_mult": NaN,
      "rank_pre_wf": 20,
      "rank_post_wf": 17,
      "rank_delta": -3
    },
    {
      "strategy": "ma_cross",
      "return_train_pct": 47.2468323200413,
      "dd_train_pct": 11.086494833012079,
      "return_test_pct": -0.7388748259302913,
      "dd_test_pct": 21.019374718289146,
      "sharpe_train": 1.7796486415760848,
      "sharpe_test": 0.07062589354103621,
      "median_pnl_per_position_train": -12.749142249302155,
      "median_pnl_per_position_test": -8.591191385137043,
      "avg_pnl_per_position_train": 12.18982607343423,
      "avg_pnl_per_position_test": 3.0091237665190174,
      "sharpe_pnl_per_position_train": 2.3305058355152717,
      "sharpe_pnl_per_position_test": 0.8039823372192733,
      "median_pnl_per_position_train_pct": -0.12749142249302156,
      "median_pnl_per_position_test_pct": -0.08591191385137043,
      "trades_train": 557,
      "trades_test": 551,
      "eligible": true,
      "trial": 116,
      "fast_period": 80.0,
      "slow_period": 201.0,
      "tp_mode": "pct",
      "tp_pct": 5.431298543795469,
      "tp_mgmt": "full",
      "tp1_close_frac": NaN,
      "tp_trail_pct": NaN,
      "sl_type": "pct",
      "sl_trailing": true,
      "exit_on_flat": true,
      "sl_pct": 7.154788387920263,
      "pm_mode": "martingale",
      "tp_rr": NaN,
      "martingale_multiplier": 1.5465972023482146,
      "martingale_max_steps": 10.0,
      "rsi_period": NaN,
      "rsi_low_th": NaN,
      "rsi_high_th": NaN,
      "grid_max_adds": NaN,
      "grid_spacing_pct": NaN,
      "grid_size_multiplier": NaN,
      "sl_atr_period": NaN,
      "sl_atr_mult": NaN,
      "rank_pre_wf": 19,
      "rank_post_wf": 18,
      "rank_delta": -1
    },
    {
      "strategy": "ma_cross",
      "return_train_pct": 21.933760435452278,
      "dd_train_pct": 9.180487142480336,
      "return_test_pct": -6.4267407498277525,
      "dd_test_pct": 22.853045797938957,
      "sharpe_train": 1.1088640743803961,
      "sharpe_test": -0.2781089105674449,
      "median_pnl_per_position_train": -15.079837036474036,
      "median_pnl_per_position_test": -9.970175189102457,
      "avg_pnl_per_position_train": 7.055649221774835,
      "avg_pnl_per_position_test": 1.4019614679128414,
      "sharpe_pnl_per_position_train": 1.767734492275375,
      "sharpe_pnl_per_position_test": 0.48524412695222413,
      "median_pnl_per_position_train_pct": -0.15079837036474036,
      "median_pnl_per_position_test_pct": -0.09970175189102456,
      "trades_train": 534,
      "trades_test": 528,
      "eligible": true,
      "trial": 421,
      "fast_period": 80.0,
      "slow_period": 203.0,
      "tp_mode": "rr",
      "tp_pct": NaN,
      "tp_mgmt": "full",
      "tp1_close_frac": NaN,
      "tp_trail_pct": NaN,
      "sl_type": "pct",
      "sl_trailing": true,
      "exit_on_flat": false,
      "sl_pct": 4.350120317488222,
      "pm_mode": "martingale",
      "tp_rr": 3.1607931386153,
      "martingale_multiplier": 1.1884296649192896,
      "martingale_max_steps": 8.0,
      "rsi_period": NaN,
      "rsi_low_th": NaN,
      "rsi_high_th": NaN,
      "grid_max_adds": NaN,
      "grid_spacing_pct": NaN,
      "grid_size_multiplier": NaN,
      "sl_atr_period": NaN,
      "sl_atr_mult": NaN,
      "rank_pre_wf": 21,
      "rank_post_wf": 19,
      "rank_delta": -2
    },
    {
      "strategy": "ma_cross",
      "return_train_pct": 89.97186327889304,
      "dd_train_pct": 18.80400906523426,
      "return_test_pct": -5.020039576811374,
      "dd_test_pct": 33.92713034115616,
      "sharpe_train": 1.9753537795579683,
      "sharpe_test": -0.01829171906235673,
      "median_pnl_per_position_train": -16.7420948861536,
      "median_pnl_per_position_test": -10.813182210253826,
      "avg_pnl_per_position_train": 23.921273424012735,
      "avg_pnl_per_position_test": 3.1160511177395582,
      "sharpe_pnl_per_position_train": 2.425010314570867,
      "sharpe_pnl_per_position_test": 0.6698897528556309,
      "median_pnl_per_position_train_pct": -0.167420948861536,
      "median_pnl_per_position_test_pct": -0.10813182210253826,
      "trades_train": 516,
      "trades_test": 519,
      "eligible": true,
      "trial": 458,
      "fast_period": 80.0,
      "slow_period": 201.0,
      "tp_mode": "pct",
      "tp_pct": 4.048882426868911,
      "tp_mgmt": "partial_trailing",
      "tp1_close_frac": 0.18186727947211,
      "tp_trail_pct": 4.9290001823283305,
      "sl_type": "pct",
      "sl_trailing": false,
      "exit_on_flat": true,
      "sl_pct": 6.375628827223881,
      "pm_mode": "martingale",
      "tp_rr": NaN,
      "martingale_multiplier": 2.8882584041756263,
      "martingale_max_steps": 9.0,
      "rsi_period": NaN,
      "rsi_low_th": NaN,
      "rsi_high_th": NaN,
      "grid_max_adds": NaN,
      "grid_spacing_pct": NaN,
      "grid_size_multiplier": NaN,
      "sl_atr_period": NaN,
      "sl_atr_mult": NaN,
      "rank_pre_wf": 22,
      "rank_post_wf": 20,
      "rank_delta": -2
    },
    {
      "strategy": "ma_cross",
      "return_train_pct": 84.63731073650114,
      "dd_train_pct": 16.458367682704413,
      "return_test_pct": 8.790053554528265,
      "dd_test_pct": 29.900174298221415,
      "sharpe_train": 1.8991949676688653,
      "sharpe_test": 0.43007934579459495,
      "median_pnl_per_position_train": -21.1027432076772,
      "median_pnl_per_position_test": -12.194202338565988,
      "avg_pnl_per_position_train": 22.631448009452388,
      "avg_pnl_per_position_test": 5.8249769128285065,
      "sharpe_pnl_per_position_train": 2.4069907924882816,
      "sharpe_pnl_per_position_test": 1.1416314402650034,
      "median_pnl_per_position_train_pct": -0.21102743207677202,
      "median_pnl_per_position_test_pct": -0.12194202338565989,
      "trades_train": 539,
      "trades_test": 549,
      "eligible": true,
      "trial": 465,
      "fast_period": 77.0,
      "slow_period": 200.0,
      "tp_mode": "rr",
      "tp_pct": NaN,
      "tp_mgmt": "partial_trailing",
      "tp1_close_frac": 0.848306416111297,
      "tp_trail_pct": 0.1473897569691395,
      "sl_type": "pct",
      "sl_trailing": false,
      "exit_on_flat": false,
      "sl_pct": 6.867495813820624,
      "pm_mode": "martingale",
      "tp_rr": 1.0661228109897827,
      "martingale_multiplier": 3.466178429294099,
      "martingale_max_steps": 2.0,
      "rsi_period": NaN,
      "rsi_low_th": NaN,
      "rsi_high_th": NaN,
      "grid_max_adds": NaN,
      "grid_spacing_pct": NaN,
      "grid_size_multiplier": NaN,
      "sl_atr_period": NaN,
      "sl_atr_mult": NaN,
      "rank_pre_wf": 23,
      "rank_post_wf": 21,
      "rank_delta": -2
    },
    {
      "strategy": "rsi_reversion",
      "return_train_pct": 8.20970734614248,
      "dd_train_pct": 2.39475952825738,
      "return_test_pct": -3.782906733130098,
      "dd_test_pct": 4.8697813270514265,
      "sharpe_train": 2.264757660661726,
      "sharpe_test": -0.821554399481578,
      "median_pnl_per_position_train": 57.88465747785187,
      "median_pnl_per_position_test": -20.928871547784816,
      "avg_pnl_per_position_train": 52.18358940767601,
      "avg_pnl_per_position_test": -19.498118798044725,
      "sharpe_pnl_per_position_train": 2.307920805840975,
      "sharpe_pnl_per_position_test": -0.6096631978487076,
      "median_pnl_per_position_train_pct": 0.5788465747785186,
      "median_pnl_per_position_test_pct": -0.20928871547784816,
      "trades_train": 18,
      "trades_test": 14,
      "eligible": true,
      "trial": 360,
      "fast_period": NaN,
      "slow_period": NaN,
      "tp_mode": "rr",
      "tp_pct": NaN,
      "tp_mgmt": "full",
      "tp1_close_frac": NaN,
      "tp_trail_pct": NaN,
      "sl_type": "atr",
      "sl_trailing": false,
      "exit_on_flat": false,
      "sl_pct": NaN,
      "pm_mode": "grid",
      "tp_rr": 0.5686986458326027,
      "martingale_multiplier": NaN,
      "martingale_max_steps": NaN,
      "rsi_period": 33.0,
      "rsi_low_th": 22.1346051164859,
      "rsi_high_th": 84.92633605937283,
      "grid_max_adds": 7.0,
      "grid_spacing_pct": 0.3806535404656916,
      "grid_size_multiplier": 1.9775600991221487,
      "sl_atr_period": 20.0,
      "sl_atr_mult": 4.1675959421202755,
      "rank_pre_wf": 2,
      "rank_post_wf": 22,
      "rank_delta": 20
    },
    {
      "strategy": "rsi_reversion",
      "return_train_pct": 16.960559835996534,
      "dd_train_pct": 5.47079367419748,
      "return_test_pct": 0.8642346777766319,
      "dd_test_pct": 5.910158828782645,
      "sharpe_train": 1.8257220148855027,
      "sharpe_test": 0.15297837240408635,
      "median_pnl_per_position_train": -106.30532154960605,
      "median_pnl_per_position_test": -100.07312378654282,
      "avg_pnl_per_position_train": 88.048333868263,
      "avg_pnl_per_position_test": -1.0784490700919813,
      "sharpe_pnl_per_position_train": 1.3508065077669273,
      "sharpe_pnl_per_position_test": -0.016872645692548698,
      "median_pnl_per_position_train_pct": -1.0630532154960606,
      "median_pnl_per_position_test_pct": -1.0007312378654283,
      "trades_train": 18,
      "trades_test": 11,
      "eligible": true,
      "trial": 15,
      "fast_period": NaN,
      "slow_period": NaN,
      "tp_mode": "rr",
      "tp_pct": NaN,
      "tp_mgmt": "full",
      "tp1_close_frac": NaN,
      "tp_trail_pct": NaN,
      "sl_type": "pct",
      "sl_trailing": false,
      "exit_on_flat": false,
      "sl_pct": 6.4000994079580735,
      "pm_mode": "none",
      "tp_rr": 4.568431936229246,
      "martingale_multiplier": NaN,
      "martingale_max_steps": NaN,
      "rsi_period": 35.0,
      "rsi_low_th": 39.71287017107015,
      "rsi_high_th": 89.00127820023857,
      "grid_max_adds": NaN,
      "grid_spacing_pct": NaN,
      "grid_size_multiplier": NaN,
      "sl_atr_period": NaN,
      "sl_atr_mult": NaN,
      "rank_pre_wf": 25,
      "rank_post_wf": 23,
      "rank_delta": -2
    },
    {
      "strategy": "rsi_reversion",
      "return_train_pct": 20.702009315174653,
      "dd_train_pct": 6.485200096130615,
      "return_test_pct": 1.4452522392301548,
      "dd_test_pct": 10.582527404815263,
      "sharpe_train": 1.673493043598989,
      "sharpe_test": 0.19827623597617078,
      "median_pnl_per_position_train": -104.99405703545202,
      "median_pnl_per_position_test": -103.13470229825447,
      "avg_pnl_per_position_train": 76.89842520337415,
      "avg_pnl_per_position_test": 6.098504809043994,
      "sharpe_pnl_per_position_train": 1.3982045292933143,
      "sharpe_pnl_per_position_test": 0.13579453830502503,
      "median_pnl_per_position_train_pct": -1.0499405703545202,
      "median_pnl_per_position_test_pct": -1.0313470229825448,
      "trades_train": 28,
      "trades_test": 28,
      "eligible": true,
      "trial": 211,
      "fast_period": NaN,
      "slow_period": NaN,
      "tp_mode": "rr",
      "tp_pct": NaN,
      "tp_mgmt": "full",
      "tp1_close_frac": NaN,
      "tp_trail_pct": NaN,
      "sl_type": "pct",
      "sl_trailing": false,
      "exit_on_flat": false,
      "sl_pct": 2.9051628507263136,
      "pm_mode": "none",
      "tp_rr": 5.092856457038706,
      "martingale_multiplier": NaN,
      "martingale_max_steps": NaN,
      "rsi_period": 37.0,
      "rsi_low_th": 27.353961171215524,
      "rsi_high_th": 84.92633605937283,
      "grid_max_adds": NaN,
      "grid_spacing_pct": NaN,
      "grid_size_multiplier": NaN,
      "sl_atr_period": NaN,
      "sl_atr_mult": NaN,
      "rank_pre_wf": 24,
      "rank_post_wf": 24,
      "rank_delta": 0
    },
    {
      "strategy": "rsi_reversion",
      "return_train_pct": 85.26334918308606,
      "dd_train_pct": 29.56487574504157,
      "return_test_pct": -17.700556219718877,
      "dd_test_pct": 38.15810182923618,
      "sharpe_train": 1.5928063079390988,
      "sharpe_test": -0.29241769014301566,
      "median_pnl_per_position_train": -201.0711956551586,
      "median_pnl_per_position_test": -141.8451422637236,
      "avg_pnl_per_position_train": 59.996394701716746,
      "avg_pnl_per_position_test": -9.245048967999034,
      "sharpe_pnl_per_position_train": 1.3739548905181664,
      "sharpe_pnl_per_position_test": -0.30036318254003685,
      "median_pnl_per_position_train_pct": -2.010711956551586,
      "median_pnl_per_position_test_pct": -1.418451422637236,
      "trades_train": 163,
      "trades_test": 114,
      "eligible": true,
      "trial": 443,
      "fast_period": NaN,
      "slow_period": NaN,
      "tp_mode": "rr",
      "tp_pct": NaN,
      "tp_mgmt": "partial_trailing",
      "tp1_close_frac": 0.34812688489352306,
      "tp_trail_pct": 0.1957105365289818,
      "sl_type": "pct",
      "sl_trailing": false,
      "exit_on_flat": false,
      "sl_pct": 1.6650725029101021,
      "pm_mode": "martingale",
      "tp_rr": 5.79828912797576,
      "martingale_multiplier": 1.9653795049407536,
      "martingale_max_steps": 10.0,
      "rsi_period": 38.0,
      "rsi_low_th": 38.44439062008213,
      "rsi_high_th": 83.88753908168715,
      "grid_max_adds": NaN,
      "grid_spacing_pct": NaN,
      "grid_size_multiplier": NaN,
      "sl_atr_period": NaN,
      "sl_atr_mult": NaN,
      "rank_pre_wf": 26,
      "rank_post_wf": 25,
      "rank_delta": -1
    },
    {
      "strategy": "rsi_reversion",
      "return_train_pct": 51.8515792220579,
      "dd_train_pct": 20.675583547804838,
      "return_test_pct": 8.053840329769347,
      "dd_test_pct": 21.847814102911244,
      "sharpe_train": 1.621414260344644,
      "sharpe_test": 0.42199994029882637,
      "median_pnl_per_position_train": 628.7679107712522,
      "median_pnl_per_position_test": -210.80193515001503,
      "avg_pnl_per_position_train": 392.9673038744528,
      "avg_pnl_per_position_test": 52.9646276752174,
      "sharpe_pnl_per_position_train": 1.7216091002404217,
      "sharpe_pnl_per_position_test": 0.17820218407958333,
      "median_pnl_per_position_train_pct": 6.287679107712522,
      "median_pnl_per_position_test_pct": -2.1080193515001504,
      "trades_train": 14,
      "trades_test": 8,
      "eligible": true,
      "trial": 133,
      "fast_period": NaN,
      "slow_period": NaN,
      "tp_mode": "rr",
      "tp_pct": NaN,
      "tp_mgmt": "partial_trailing",
      "tp1_close_frac": 0.726395990211752,
      "tp_trail_pct": 0.19329140292540864,
      "sl_type": "pct",
      "sl_trailing": false,
      "exit_on_flat": false,
      "sl_pct": 8.265319806139443,
      "pm_mode": "grid",
      "tp_rr": 1.6405323403077487,
      "martingale_multiplier": NaN,
      "martingale_max_steps": NaN,
      "rsi_period": 33.0,
      "rsi_low_th": 29.081025492041263,
      "rsi_high_th": 84.39203712408185,
      "grid_max_adds": 4.0,
      "grid_spacing_pct": 2.1952438700307484,
      "grid_size_multiplier": 1.3116565601840438,
      "sl_atr_period": NaN,
      "sl_atr_mult": NaN,
      "rank_pre_wf": 1,
      "rank_post_wf": 26,
      "rank_delta": 25
    },
    {
      "strategy": "rsi_reversion",
      "return_train_pct": 57.05324848173008,
      "dd_train_pct": 26.938125185972318,
      "return_test_pct": -18.156000464496813,
      "dd_test_pct": 36.073497517295536,
      "sharpe_train": 1.2736658307765625,
      "sharpe_test": -0.3004883419005666,
      "median_pnl_per_position_train": -273.6427489582635,
      "median_pnl_per_position_test": -287.9959771094923,
      "avg_pnl_per_position_train": 142.14155239405156,
      "avg_pnl_per_position_test": -118.43763986885838,
      "sharpe_pnl_per_position_train": 0.9771044691319486,
      "sharpe_pnl_per_position_test": -1.0726473607572224,
      "median_pnl_per_position_train_pct": -2.736427489582635,
      "median_pnl_per_position_test_pct": -2.879959771094923,
      "trades_train": 40,
      "trades_test": 19,
      "eligible": true,
      "trial": 449,
      "fast_period": NaN,
      "slow_period": NaN,
      "tp_mode": "rr",
      "tp_pct": NaN,
      "tp_mgmt": "full",
      "tp1_close_frac": NaN,
      "tp_trail_pct": NaN,
      "sl_type": "pct",
      "sl_trailing": false,
      "exit_on_flat": false,
      "sl_pct": 3.4292022560701207,
      "pm_mode": "martingale",
      "tp_rr": 6.43964452765901,
      "martingale_multiplier": 2.1843122416668885,
      "martingale_max_steps": 10.0,
      "rsi_period": 35.0,
      "rsi_low_th": 38.44439062008213,
      "rsi_high_th": 84.92633605937283,
      "grid_max_adds": NaN,
      "grid_spacing_pct": NaN,
      "grid_size_multiplier": NaN,
      "sl_atr_period": NaN,
      "sl_atr_mult": NaN,
      "rank_pre_wf": 27,
      "rank_post_wf": 27,
      "rank_delta": 0
    }
  ],
  "global_leaderboard_file": "global_leaderboard.csv",
  "candidates_file": "candidates.csv",
  "champion": {
    "strategy": "rsi_reversion",
    "return_train_pct": 5.394403747224663,
    "dd_train_pct": 0.19832479605432587,
    "return_test_pct": 0.14164777193306222,
    "dd_test_pct": 3.537442624240905,
    "sharpe_train": 3.2324163708892124,
    "sharpe_test": 0.07149113291148967,
    "median_pnl_per_position_train": 50.473477335195795,
    "median_pnl_per_position_test": 40.90507964235443,
    "avg_pnl_per_position_train": 51.658105559609936,
    "avg_pnl_per_position_test": 9.065964113136529,
    "sharpe_pnl_per_position_train": 11.108577004136011,
    "sharpe_pnl_per_position_test": 0.3844879106069612,
    "median_pnl_per_position_train_pct": 0.504734773351958,
    "median_pnl_per_position_test_pct": 0.40905079642354436,
    "trades_train": 12,
    "trades_test": 12,
    "eligible": true,
    "trial": 447,
    "fast_period": NaN,
    "slow_period": NaN,
    "tp_mode": "rr",
    "tp_pct": NaN,
    "tp_mgmt": "full",
    "tp1_close_frac": NaN,
    "tp_trail_pct": NaN,
    "sl_type": "atr",
    "sl_trailing": false,
    "exit_on_flat": false,
    "sl_pct": NaN,
    "pm_mode": "grid",
    "tp_rr": 0.5019566305729979,
    "martingale_multiplier": NaN,
    "martingale_max_steps": NaN,
    "rsi_period": 35.0,
    "rsi_low_th": 21.76936946289403,
    "rsi_high_th": 84.39203712408185,
    "grid_max_adds": 3.0,
    "grid_spacing_pct": 0.47183977805878674,
    "grid_size_multiplier": 2.2131969678463204,
    "sl_atr_period": 23.0,
    "sl_atr_mult": 3.2160462393971967,
    "rank_pre_wf": 3,
    "rank_post_wf": 1,
    "rank_delta": -2
  }
}